[
  {
    "name": "I found interest in App Development, I really enjoy making applications.",
    "species": "Im a Beginner in App Development, Im doing my best to develop my skills in it and publish my own Application."
  },
  {
    "name": "I also found myself having an interest in Programming, but still I have so many things to learn from it.",
    "species": "I can't call myself a programmer yet, but I'm open for the possibility."
  },
  {
    "name": "As a Leader, I must provide solutions to the problem.",
    "species": "I'm a kind of person who wants to help others and provide the possible solution."
  }
]
